TwigWeb/__init__.py
TwigWeb/backend/404.html
TwigWeb/backend/__init__.py
TwigWeb/backend/response.py
TwigWeb/backend/runtime.py
TwigWeb/backend/types.py
TwigWeb/backend/util.py
TwigWeb/backend/headers/__init__.py
TwigWeb/backend/routehandler/__init__.py
TwigWeb/backend/routehandler/route.py
TwigWeb/backend/routehandler/router.py
TwigWeb/frontend/__init__.py
TwigWeb/frontend/preprocessor.py
TwigWeb-0.5.1.dist-info/LICENSE.txt
TwigWeb-0.5.1.dist-info/METADATA
TwigWeb-0.5.1.dist-info/WHEEL
TwigWeb-0.5.1.dist-info/top_level.txt
TwigWeb-0.5.1.dist-info/RECORD
