Metadata-Version: 2.1
Name: TwigWeb
Version: 0.5.1
Summary: Twig is a frontend and backend web framework utilizing the python socket module to serve http requests.
Home-page: https://github.com/FrewtyPebbles/Twig-Web-Framework
Author: William Lim
Author-email: William.Lim@csu.fullerton.edu
License: UNKNOWN
Project-URL: Bug Tracker, https://github.com/FrewtyPebbles/Twig-Web-Framework/issues
Platform: UNKNOWN
Classifier: Programming Language :: Python :: 3
Classifier: License :: OSI Approved :: MIT License
Classifier: Operating System :: OS Independent
Requires-Python: >=3.7
License-File: LICENSE.txt
